LICENSE
README.MD
setup.cfg
setup.py
pokie_gunicorn/__init__.py
pokie_gunicorn/config.py
pokie_gunicorn/constants.py
pokie_gunicorn/module.py
pokie_gunicorn.egg-info/PKG-INFO
pokie_gunicorn.egg-info/SOURCES.txt
pokie_gunicorn.egg-info/dependency_links.txt
pokie_gunicorn.egg-info/not-zip-safe
pokie_gunicorn.egg-info/requires.txt
pokie_gunicorn.egg-info/top_level.txt
pokie_gunicorn/cli/__init__.py
pokie_gunicorn/cli/run.py