Metadata-Version: 2.1
Name: pokie-gunicorn
Version: 1.1.1
Summary: Gunicorn embedding module for pokie
Home-page: https://git.oddbit.org/OddBit/pokie-gunicorn
Author: João Pinheiro
License: BSD-3-Clause
Project-URL: Source, https://git.oddbit.org/OddBit/pokie-gunicorn/
Classifier: Environment :: Web Environment
Classifier: Development Status :: 5 - Production/Stable
Classifier: Intended Audience :: Developers
Classifier: License :: OSI Approved :: BSD License
Classifier: Operating System :: OS Independent
Classifier: Programming Language :: Python
Classifier: Programming Language :: Python :: 3.10
Classifier: Programming Language :: Python :: 3.11
Classifier: Programming Language :: Python :: 3.12
Classifier: Topic :: Internet :: WWW/HTTP
Classifier: Topic :: Internet :: WWW/HTTP :: Dynamic Content
Classifier: Topic :: Internet :: WWW/HTTP :: WSGI
Classifier: Topic :: Software Development :: Libraries :: Application Frameworks
Classifier: Topic :: Software Development :: Libraries :: Python Modules
Requires-Python: >=3.10
License-File: LICENSE
Requires-Dist: rick>=0.6.0
Requires-Dist: pokie>=0.5.2
Requires-Dist: gunicorn>=22.0.0
Requires-Dist: tabulate>=0.9.0
